lmagent/__init__.py
lmagent/config.py
lmagent/demo.py
lmagent/message.py
lmagent/msghub.py
LMagent-0.1.103.dist-info/LICENSE
LMagent-0.1.103.dist-info/METADATA
LMagent-0.1.103.dist-info/WHEEL
LMagent-0.1.103.dist-info/top_level.txt
LMagent-0.1.103.dist-info/RECORD
