Metadata-Version: 2.1
Name: LMagent
Version: 0.1.103
Summary: A large chinese free language chain tools,you can get free API from:open.bigmodel.cn
Home-page: https://github.com/virgo777/lmagent/
Author: xiaohuaWang
Author-email: xiaohuaWang <5847713@qq.com>
Project-URL: Homepage, https://github.com/virgo777/lmagent
Project-URL: Bug Tracker, https://github.com/virgo777/lmagent/issues
Classifier: Programming Language :: Python :: 3
Classifier: License :: OSI Approved :: MIT License
Classifier: Operating System :: OS Independent
Requires-Python: >=3
License-File: LICENSE
Requires-Dist: uvicorn >=0.23.2
Requires-Dist: fastapi >=0.108.0
Requires-Dist: zhipuai >=2.0.1
Requires-Dist: gradio
Requires-Dist: requests
Requires-Dist: numpy
